{
  "pk": {
    "S": "3444a5c1843b11b61de6a8474b42959e5e99c6e247ed97ab9e743c0b"
  },
  "adaHandle": {
    "S": "000de14074745f74657374"
  },
  "banner": {
    "S": ""
  },
  "primary_color": {
    "S": "#2457f2"
  },
  "secondary_color": {
    "S": "#dce0ef"
  },
  "profile": {
    "S": ""
  },
  "asset": {
    "M": {
      "AssetId": {
        "S": "99e7cd5c0aca25bc3e90be7e318326a188f913a07bbfe09b3bace0d4.545450726576696577"
      },
      "AssetName": {
        "S": "TTPreview"
      },
      "Decimals": {
        "N": "6"
      },
      "Logo": {
        "NULL": true
      },
      "MintDate": {
        "M": {
          "Slot": {
            "S": "44512439"
          },
          "SlotOffset": {
            "N": "1666656000"
          }
        }
      },
      "PolicyId": {
        "S": "99e7cd5c0aca25bc3e90be7e318326a188f913a07bbfe09b3bace0d4"
      },
      "Ticker": {
        "S": "TTPRE"
      },
      "TotalSupply": {
        "S": "10001000000000"
      }
    }
  },
  "createdDate": {
    "M": {
      "Slot": {
        "S": "44512439"
      },
      "SlotOffset": {
        "N": "1666656000"
      }
    }
  },
  "creationTxHash": {
    "S": "0eb856e304057c69a43c4d727aaa7b89ea4b7a6557ae91d2e20e2e8f5dd6c0d8"
  },
  "endDate": {
    "M": {
      "Slot": {
        "S": "44514461"
      },
      "SlotOffset": {
        "N": "1666656000"
      }
    }
  },
  "finalTxHash": {
    "NULL": true
  },
  "fundingAllocations": {
    "L": [
      {
        "M": {
          "Label": {
            "S": "SS"
          },
          "Percentage": {
            "N": "1"
          }
        }
      }
    ]
  },
  "lastCallDate": {
    "M": {
      "Slot": {
        "S": "44428061"
      },
      "SlotOffset": {
        "N": "1666656000"
      }
    }
  },
  "openDate": {
    "M": {
      "Slot": {
        "S": "44512439"
      },
      "SlotOffset": {
        "N": "1666656000"
      }
    }
  },
  "parameters": {
    "M": {
      "beneficiaryAddress": {
        "S": "addr_test1qrp8nglm8d8x9w783c5g0qa4spzaft5z5xyx0kp495p8wksjrlfzuz6h4ssxlm78v0utlgrhryvl2gvtgp53a6j9zngqtjfk6s"
      },
      "foldFee": {
        "N": "1000000"
      },
      "minUTXO": {
        "N": "3000000"
      },
      "penaltyAddress": {
        "S": "addr_test1qrp8nglm8d8x9w783c5g0qa4spzaft5z5xyx0kp495p8wksjrlfzuz6h4ssxlm78v0utlgrhryvl2gvtgp53a6j9zngqtjfk6s"
      },
      "penaltyPercentage": {
        "N": "0.25"
      },
      "poolFee": {
        "M": {
          "Denominator": {
            "N": "1000"
          },
          "Numerator": {
            "N": "30"
          }
        }
      }
    }
  },
  "poolTxHash": {
    "NULL": true
  },
  "projectDetails": {
    "M": {
      "Description": {
        "S": "The Preview Test is an example project description that goes here, allowing users to more easily see the details."
      },
      "Handle": {
        "S": "yes"
      },
      "Name": {
        "S": "Preview Test"
      },
      "Socials": {
        "L": [
          {
            "M": {
              "Name": {
                "S": "Reddit"
              },
              "Url": {
                "S": "https://example.com"
              }
            }
          },
          {
            "M": {
              "Name": {
                "S": "Telegram"
              },
              "Url": {
                "S": "https://example.com"
              }
            }
          }
        ]
      },
      "Team": {
        "M": {
          "Company": {
            "S": "undefined, Inc."
          },
          "Members": {
            "L": [
              {
                "M": {
                  "Name": {
                    "S": "Lorem Ipsum"
                  },
                  "Role": {
                    "S": "CEO"
                  },
                  "Social": {
                    "NULL": true
                  }
                }
              }
            ]
          },
          "Other": {
            "L": [
              {
                "S": "AP1"
              }
            ]
          },
          "Socials": {
            "NULL": true
          }
        }
      },
      "Tokenomics": {
        "L": [
          {
            "M": {
              "Label": {
                "S": "DAO Treasury"
              },
              "Percentage": {
                "N": "50"
              }
            }
          },
          {
            "M": {
              "Label": {
                "S": "Airdrop"
              },
              "Percentage": {
                "N": "15"
              }
            }
          },
          {
            "M": {
              "Label": {
                "S": "Governance"
              },
              "Percentage": {
                "N": "10"
              }
            }
          },
          {
            "M": {
              "Label": {
                "S": "Team"
              },
              "Percentage": {
                "N": "5"
              }
            }
          },
          {
            "M": {
              "Label": {
                "S": "Protocol Liquidity"
              },
              "Percentage": {
                "N": "12"
              }
            }
          },
          {
            "M": {
              "Label": {
                "S": "Taste Test"
              },
              "Percentage": {
                "N": "8"
              }
            }
          }
        ]
      }
    }
  },
  "projectTokens": {
    "N": "10001000000000"
  },
  "scripts": {
    "M": {
      "CollectFoldPolicy": {
        "M": {
          "purpose": {
            "S": "CollectFoldPolicy"
          },
          "scriptBytes": {
            "NULL": true
          },
          "scriptHash": {
            "S": "2e2b3a9037088e03e1fe2c72632649156cc27cee570bf791011cc938"
          },
          "utxo": {
            "M": {
              "index": {
                "N": "0"
              },
              "txId": {
                "S": "5901fba2c11ed5f08142c5c4dea58ba7a962cdf5d63e2d3e8165547ed58b6457"
              }
            }
          }
        }
      },
      "CollectFoldValidator": {
        "M": {
          "purpose": {
            "S": "CollectFoldValidator"
          },
          "scriptBytes": {
            "NULL": true
          },
          "scriptHash": {
            "S": "c678ec7ef7a06c0bc7af211c2019a660aa4e4c60e4100abd94136136"
          },
          "utxo": {
            "M": {
              "index": {
                "N": "0"
              },
              "txId": {
                "S": "c4d7420000bfda18251c5fe2ab77d95ed1da7b99ab5ca7f8f9b5a7554c9853e7"
              }
            }
          }
        }
      },
      "RewardFoldPolicy": {
        "M": {
          "purpose": {
            "S": "RewardFoldPolicy"
          },
          "scriptBytes": {
            "NULL": true
          },
          "scriptHash": {
            "S": "6b0145b0615081bd7953f481a05053b82b33ddda7bdaf1c60fc91523"
          },
          "utxo": {
            "M": {
              "index": {
                "N": "0"
              },
              "txId": {
                "S": "1a8b2de27c848636953de28e921ce544882445c94778f6c45f1e45ca5d98fe07"
              }
            }
          }
        }
      },
      "RewardFoldValidator": {
        "M": {
          "purpose": {
            "S": "RewardFoldValidator"
          },
          "scriptBytes": {
            "NULL": true
          },
          "scriptHash": {
            "S": "9651c785b61b71d3a158dfa9e25aaf4f9ecc4ef7741070e029ae8767"
          },
          "utxo": {
            "M": {
              "index": {
                "N": "0"
              },
              "txId": {
                "S": "3a6a740bb634d0f959f791039e5e0104d783abfdcb4b75ca1b38a94431996186"
              }
            }
          }
        }
      },
      "TasteTestPolicy": {
        "M": {
          "purpose": {
            "S": "TasteTestPolicy"
          },
          "scriptBytes": {
            "NULL": true
          },
          "scriptHash": {
            "S": "54f54e4d8a05cf4a8041354794b64bf2552dfd292c73899b763008c5"
          },
          "utxo": {
            "M": {
              "index": {
                "N": "0"
              },
              "txId": {
                "S": "b749540c264d11319727f86ad869bdeea8eeac41816084c2911d5cc82b0cf86a"
              }
            }
          }
        }
      },
      "TasteTestValidator": {
        "M": {
          "purpose": {
            "S": "TasteTestValidator"
          },
          "scriptBytes": {
            "NULL": true
          },
          "scriptHash": {
            "S": "deeb63136daf7102d6bb59ca87bc46f8ed93738a478fab19d627455b"
          },
          "utxo": {
            "M": {
              "index": {
                "N": "0"
              },
              "txId": {
                "S": "22e406b8aed5101781d4d8b69216375b5e2918d22f5863dd12bbe32abdabdb4a"
              }
            }
          }
        }
      },
      "TasteTestStakeValidator": {
        "M": {
          "purpose": {
            "S": "TasteTestStakeValidator"
          },
          "scriptBytes": {
            "NULL": true
          },
          "scriptHash": {
            "S": "5a02f88bdbb3d41508432eb08ecc2450ca05975caf353668e3c3fb77"
          },
          "utxo": {
            "M": {
              "index": {
                "N": "0"
              },
              "txId": {
                "S": "cc6ed3a2e92bf405fb1e2741eee2bae2408324e06814ca26d0bafb63da618e80"
              }
            }
          }
        }
      },
      "TokenHolderPolicy": {
        "M": {
          "purpose": {
            "S": "TokenHolderPolicy"
          },
          "scriptBytes": {
            "NULL": true
          },
          "scriptHash": {
            "S": "7d520a2e53ed3bf34d89fb7915f62dfe3cc411237b6c33404507cf53"
          },
          "utxo": {
            "M": {
              "index": {
                "N": "0"
              },
              "txId": {
                "S": "97ea13a015623ea4cd890d77619769ba54870d0c2a0da9119393c6af48cc9043"
              }
            }
          }
        }
      },
      "TokenHolderValidator": {
        "M": {
          "purpose": {
            "S": "TokenHolderValidator"
          },
          "scriptBytes": {
            "NULL": true
          },
          "scriptHash": {
            "S": "8203cebfe7bab29e8ce9bac2e27dc3cfdd3f1d98c71ffe4b26628090"
          },
          "utxo": {
            "M": {
              "index": {
                "N": "0"
              },
              "txId": {
                "S": "3c6f3727fa6119157fb0cfbc7161b908fd9d5e612b510fdb2d87bde8fb62d484"
              }
            }
          }
        }
      }
    }
  },
  "slug": {
    "S": "preview-test"
  },
  "type": {
    "S": "Liquidity"
  },
  "vestingSchedule": {
    "L": [
      {
        "M": {
          "Address": {
            "S": "addr1justoneparty"
          },
          "Amount": {
            "S": "1000000"
          },
          "Label": {
            "S": "Just One Party"
          },
          "ReleaseDate": {
            "M": {
              "Slot": {
                "S": "53152439"
              },
              "SlotOffset": {
                "N": "1666656000"
              }
            }
          }
        }
      }
    ]
  }
}